{
  "domain": "www.skool.com",
  "lastUpdated": "2025-06-18T21:48:44.426Z",
  "version": 95,
  "trainedComponents": [
    {
      "id": "Settings",
      "pageUrl": "https://www.skool.com/testxx-7587",
      "pagePath": "/testxx-7587",
      "type": "modal",
      "name": "Settings",
      "selector": ".styled__TabModalDesktop-sc-1p35nnr-1",
      "trainingData": {
        "componentType": "modal",
        "componentName": "Settings",
        "tagName": "DIV",
        "className": "styled__TabModalDesktop-sc-1p35nnr-1 fxoRNW",
        "id": "",
        "left": 103,
        "top": 12,
        "width": 1074,
        "height": 696,
        "zIndex": "auto",
        "position": "static",
        "modalScore": 10,
        "contextElements": [
          {
            "tagName": "div",
            "className": "styled__MetricItems-sc-118pr9v-3 iDbXyO",
            "position": "static",
            "zIndex": 0,
            "level": 1,
            "relationship": "parent"
          },
          {
            "tagName": "div",
            "className": "styled__BoxWrapper-sc-esqoz3-0 jSzCth",
            "position": "static",
            "zIndex": 0,
            "level": 2,
            "relationship": "parent"
          },
          {
            "tagName": "div",
            "className": "styled__BoxWrapper-sc-esqoz3-0 cXMjcI Column-sc-1h1w9fe-0 duwkcK",
            "position": "static",
            "zIndex": 0,
            "level": 3,
            "relationship": "parent"
          },
          {
            "tagName": "div",
            "className": "styled__MetricItem-sc-118pr9v-4 bGqEDe",
            "position": "static",
            "zIndex": 0,
            "level": 0,
            "relationship": "sibling"
          },
          {
            "tagName": "div",
            "className": "styled__MetricItem-sc-118pr9v-4 bGqEDe",
            "position": "static",
            "zIndex": 0,
            "level": 0,
            "relationship": "sibling"
          }
        ]
      },
      "createdAt": "2025-06-18T21:06:44.500Z",
      "lastUpdated": "2025-06-18T21:06:44.500Z"
    },
    {
      "id": "Edit_Course",
      "pageUrl": "https://www.skool.com/testxx-7587/classroom",
      "pagePath": "/testxx-7587/classroom",
      "type": "modal",
      "name": "Edit Course",
      "selector": ".styled__ModalWrapper-sc-7eym6d-0",
      "trainingData": {
        "componentType": "modal",
        "componentName": "Edit Course",
        "tagName": "DIV",
        "className": "styled__ModalWrapper-sc-7eym6d-0 dZKBqb",
        "id": "",
        "left": 400,
        "top": 57.55859375,
        "width": 800,
        "height": 784.873046875,
        "zIndex": "auto",
        "position": "relative",
        "modalScore": 10,
        "contextElements": [
          {
            "tagName": "label",
            "className": "styled__PermissionOption-sc-1qwbnnp-9 ikZrt",
            "position": "static",
            "zIndex": 0,
            "level": 1,
            "relationship": "parent"
          },
          {
            "tagName": "form",
            "className": "styled__PermissionsForm-sc-1qwbnnp-8 ixaNKR",
            "position": "static",
            "zIndex": 0,
            "level": 2,
            "relationship": "parent"
          },
          {
            "tagName": "div",
            "className": "styled__ModalBody-sc-7eym6d-3 biFwPS",
            "position": "static",
            "zIndex": 0,
            "level": 3,
            "relationship": "parent"
          },
          {
            "tagName": "button",
            "className": "styled__SelectionWrapper-sc-ojqj0m-1 gXYuRV",
            "position": "static",
            "zIndex": 0,
            "level": 0,
            "relationship": "sibling"
          }
        ]
      },
      "createdAt": "2025-06-18T21:11:08.891Z",
      "lastUpdated": "2025-06-18T21:11:08.891Z"
    },
    {
      "id": "Level_Unlock",
      "pageUrl": "https://www.skool.com/testxx-7587/classroom",
      "pagePath": "/testxx-7587/classroom",
      "type": "modal",
      "name": "Level Unlock",
      "selector": ".styled__PermissionOption-sc-1qwbnnp-9",
      "trainingData": {
        "componentType": "modal",
        "componentName": "Level Unlock",
        "tagName": "LABEL",
        "className": "styled__PermissionOption-sc-1qwbnnp-9 ikZrt",
        "id": "",
        "left": 580.048828125,
        "top": 392.24609375,
        "width": 146.806640625,
        "height": 116.962890625,
        "zIndex": "auto",
        "position": "static",
        "modalScore": 0,
        "contextElements": [
          {
            "tagName": "label",
            "className": "styled__PermissionOption-sc-1qwbnnp-9 ikZrt",
            "position": "static",
            "zIndex": 0,
            "level": 1,
            "relationship": "parent"
          },
          {
            "tagName": "form",
            "className": "styled__PermissionsForm-sc-1qwbnnp-8 ixaNKR",
            "position": "static",
            "zIndex": 0,
            "level": 2,
            "relationship": "parent"
          },
          {
            "tagName": "div",
            "className": "styled__ModalBody-sc-7eym6d-3 biFwPS",
            "position": "static",
            "zIndex": 0,
            "level": 3,
            "relationship": "parent"
          },
          {
            "tagName": "button",
            "className": "styled__SelectionWrapper-sc-ojqj0m-1 gXYuRV",
            "position": "static",
            "zIndex": 0,
            "level": 0,
            "relationship": "sibling"
          }
        ]
      },
      "createdAt": "2025-06-18T21:20:41.087Z",
      "lastUpdated": "2025-06-18T21:20:41.087Z"
    },
    {
      "id": "Profile_Picture",
      "pageUrl": "https://www.skool.com/testxx-7587/-/leaderboards",
      "pagePath": "/testxx-7587/-/leaderboards",
      "type": "modal",
      "name": "Profile Picture",
      "selector": ".styled__UserInfoWrapper-sc-hb97og-3",
      "trainingData": {
        "componentType": "modal",
        "componentName": "Profile Picture",
        "tagName": "DIV",
        "className": "styled__UserInfoWrapper-sc-hb97og-3 ilRdrF",
        "id": "",
        "left": 274.12109375,
        "top": 197.63671875,
        "width": 352.333984375,
        "height": 300.712890625,
        "zIndex": "auto",
        "position": "relative",
        "modalScore": 10,
        "contextElements": [
          {
            "tagName": "div",
            "className": "styled__AvatarWrapper-sc-1o1lx2q-0 kdtNwu",
            "position": "relative",
            "zIndex": 0,
            "level": 1,
            "relationship": "parent"
          },
          {
            "tagName": "a",
            "className": "styled__ChildrenLink-sc-1brgbbt-1 fQYQam",
            "position": "static",
            "zIndex": 0,
            "level": 2,
            "relationship": "parent"
          },
          {
            "tagName": "div",
            "className": "styled__UserInfoWrapper-sc-hb97og-3 ilRdrF",
            "position": "relative",
            "zIndex": 0,
            "level": 3,
            "relationship": "parent"
          },
          {
            "tagName": "span",
            "className": "styled__AvatarWrapper-sc-1ruw40r-0 BUAVN",
            "position": "relative",
            "zIndex": 0,
            "level": 0,
            "relationship": "sibling"
          },
          {
            "tagName": "div",
            "className": "styled__BadgeWrapper-sc-1o1lx2q-2 iVmISE",
            "position": "absolute",
            "zIndex": 1,
            "level": 0,
            "relationship": "sibling"
          }
        ]
      },
      "createdAt": "2025-06-18T21:23:01.472Z",
      "lastUpdated": "2025-06-18T21:23:01.472Z"
    },
    {
      "id": "Levels",
      "pageUrl": "https://www.skool.com/testxx-7587/-/leaderboards",
      "pagePath": "/testxx-7587/-/leaderboards",
      "type": "modal",
      "name": "Levels",
      "selector": ".styled__LevelBlocksWrapper-sc-hb97og-8",
      "trainingData": {
        "componentType": "modal",
        "componentName": "Levels",
        "tagName": "DIV",
        "className": "styled__LevelBlocksWrapper-sc-hb97og-8 dmSCWh",
        "id": "",
        "left": 626.455078125,
        "top": 204.16015625,
        "width": 699.4140625,
        "height": 287.666015625,
        "zIndex": "auto",
        "position": "static",
        "modalScore": 10,
        "contextElements": [
          {
            "tagName": "div",
            "className": "styled__ProgressCardRightCol-sc-hb97og-7 ljFapR",
            "position": "static",
            "zIndex": 0,
            "level": 1,
            "relationship": "parent"
          },
          {
            "tagName": "div",
            "className": "styled__CardWrapper-sc-jrheml-0 hesuCC styled__GamificationProgressCard-sc-hb97og-0 hAOsjp",
            "position": "relative",
            "zIndex": 0,
            "level": 2,
            "relationship": "parent"
          },
          {
            "tagName": "div",
            "className": "styled__Column-sc-hb97og-17 cwfpji",
            "position": "static",
            "zIndex": 0,
            "level": 3,
            "relationship": "parent"
          }
        ]
      },
      "createdAt": "2025-06-18T21:24:07.282Z",
      "lastUpdated": "2025-06-18T21:24:07.282Z"
    },
    {
      "id": "Add_Price",
      "pageUrl": "https://www.skool.com/testxx-7587",
      "pagePath": "/testxx-7587",
      "type": "modal",
      "name": "Add Price",
      "selector": ".styled__ModalWrapper-sc-7eym6d-0",
      "trainingData": {
        "componentType": "modal",
        "componentName": "Add Price",
        "tagName": "DIV",
        "className": "styled__ModalWrapper-sc-7eym6d-0 dZKBqb",
        "id": "",
        "left": 572.998046875,
        "top": 233.671875,
        "width": 453.994140625,
        "height": 432.65625,
        "zIndex": "auto",
        "position": "relative",
        "modalScore": 10,
        "contextElements": [
          {
            "tagName": "div",
            "className": "styled__AddPriceModalWrapper-sc-1w5znzb-0 kBdbrp",
            "position": "static",
            "zIndex": 0,
            "level": 1,
            "relationship": "parent"
          },
          {
            "tagName": "div",
            "className": "styled__ModalBody-sc-7eym6d-3 biFwPS",
            "position": "static",
            "zIndex": 0,
            "level": 2,
            "relationship": "parent"
          },
          {
            "tagName": "form",
            "className": "",
            "position": "static",
            "zIndex": 0,
            "level": 3,
            "relationship": "parent"
          },
          {
            "tagName": "div",
            "className": "styled__InputContainer-sc-1saiqqb-5 jxyKwe",
            "position": "static",
            "zIndex": 0,
            "level": 0,
            "relationship": "sibling"
          },
          {
            "tagName": "div",
            "className": "styled__Disclaimers-sc-1w5znzb-4 gaEuSN",
            "position": "static",
            "zIndex": 0,
            "level": 0,
            "relationship": "sibling"
          }
        ]
      },
      "createdAt": "2025-06-18T21:32:34.525Z",
      "lastUpdated": "2025-06-18T21:32:34.525Z"
    },
    {
      "id": "Traffic",
      "pageUrl": "https://www.skool.com/testxx-7587",
      "pagePath": "/testxx-7587",
      "type": "modal",
      "name": "Traffic",
      "selector": ".styled__MetricItem-sc-118pr9v-4",
      "trainingData": {
        "componentType": "modal",
        "componentName": "Traffic",
        "tagName": "DIV",
        "className": "styled__MetricItem-sc-118pr9v-4 bGqEDe",
        "id": "",
        "left": 658,
        "top": 333,
        "width": 234,
        "height": 87,
        "zIndex": "auto",
        "position": "static",
        "modalScore": 10,
        "contextElements": [
          {
            "tagName": "div",
            "className": "styled__MetricItem-sc-118pr9v-4 bGqEDe",
            "position": "static",
            "zIndex": 0,
            "level": 1,
            "relationship": "parent"
          },
          {
            "tagName": "div",
            "className": "styled__MetricItems-sc-118pr9v-3 iDbXyO",
            "position": "static",
            "zIndex": 0,
            "level": 2,
            "relationship": "parent"
          },
          {
            "tagName": "div",
            "className": "styled__BoxWrapper-sc-esqoz3-0 jSzCth",
            "position": "static",
            "zIndex": 0,
            "level": 3,
            "relationship": "parent"
          },
          {
            "tagName": "div",
            "className": "styled__MetricLabel-sc-118pr9v-6 jAyTkG",
            "position": "static",
            "zIndex": 0,
            "level": 0,
            "relationship": "sibling"
          }
        ]
      },
      "createdAt": "2025-06-18T21:48:44.426Z",
      "lastUpdated": "2025-06-18T21:48:44.426Z"
    }
  ]
}